coax/__init__.py
coax/typing.py
coax/_base/__init__.py
coax/_base/errors.py
coax/_base/test_case.py
coax/_base/mixins/__init__.py
coax/_base/mixins/_add_orig_to_info.py
coax/_base/mixins/_copy.py
coax/_base/mixins/_logger.py
coax/_base/mixins/_random_state.py
coax/_core/__init__.py
coax/_core/base_func.py
coax/_core/base_stochastic_func_type1.py
coax/_core/base_stochastic_func_type2.py
coax/_core/policy.py
coax/_core/policy_test.py
coax/_core/q.py
coax/_core/q_test.py
coax/_core/random_policy.py
coax/_core/random_policy_test.py
coax/_core/reward_function.py
coax/_core/stochastic_q.py
coax/_core/stochastic_q_test.py
coax/_core/stochastic_reward_function.py
coax/_core/stochastic_transition_model.py
coax/_core/stochastic_transition_model_test.py
coax/_core/stochastic_v.py
coax/_core/stochastic_v_test.py
coax/_core/successor_state_q.py
coax/_core/transition_model.py
coax/_core/transition_model_test.py
coax/_core/v.py
coax/_core/v_test.py
coax/_core/value_based_policy.py
coax/_core/value_based_policy_test.py
coax/_core/worker.py
coax/envs/__init__.py
coax/envs/_connect_four.py
coax/experience_replay/__init__.py
coax/experience_replay/_base.py
coax/experience_replay/_prioritized.py
coax/experience_replay/_prioritized_test.py
coax/experience_replay/_simple.py
coax/model_updaters/__init__.py
coax/model_updaters/_model_updater.py
coax/model_updaters/_model_updater_test.py
coax/policy_objectives/__init__.py
coax/policy_objectives/_base.py
coax/policy_objectives/_deterministic_pg.py
coax/policy_objectives/_deterministic_pg_test.py
coax/policy_objectives/_ppo_clip.py
coax/policy_objectives/_ppo_clip_test.py
coax/policy_objectives/_soft_pg.py
coax/policy_objectives/_soft_pg_test.py
coax/policy_objectives/_vanilla_pg.py
coax/policy_objectives/_vanilla_pg_test.py
coax/proba_dists/__init__.py
coax/proba_dists/_base.py
coax/proba_dists/_categorical.py
coax/proba_dists/_composite.py
coax/proba_dists/_composite_test.py
coax/proba_dists/_discretized_interval.py
coax-0.1.13.dist-info/LICENSE
coax-0.1.13.dist-info/METADATA
coax-0.1.13.dist-info/WHEEL
coax-0.1.13.dist-info/top_level.txt
coax-0.1.13.dist-info/zip-safe
coax-0.1.13.dist-info/RECORD
