Metadata-Version: 2.1
Name: coax
Version: 0.1.13
Summary: Plug-n-play reinforcement learning with Gymnasium and JAX
Home-page: https://coax.readthedocs.io
Author: Kristian Holsheimer
Author-email: kristian.holsheimer@gmail.com
License: MIT
Platform: UNKNOWN
Classifier: Development Status :: 1 - Planning
Classifier: Environment :: GPU :: NVIDIA CUDA
Classifier: Framework :: Flake8
Classifier: Framework :: IPython
Classifier: Framework :: Jupyter
Classifier: Framework :: Pytest
Classifier: Framework :: Sphinx
Classifier: Intended Audience :: Science/Research
Classifier: License :: OSI Approved :: MIT License
Classifier: Natural Language :: English
Classifier: Operating System :: MacOS :: MacOS X
Classifier: Operating System :: POSIX :: Linux
Classifier: Programming Language :: Python :: 3.6
Classifier: Programming Language :: Python :: 3.7
Classifier: Programming Language :: Python :: 3.8
Classifier: Topic :: Scientific/Engineering :: Artificial Intelligence
Requires-Python: ~=3.6
Requires-Dist: Pillow (>=7.1.2)
Requires-Dist: gymnasium[accept-rom-license,atari,box2d] (>=0.26.0)
Requires-Dist: numpy (>=1.21.6)
Requires-Dist: scipy (>=1.7.3)
Requires-Dist: pandas (>=1.3.5)
Requires-Dist: dm-haiku (>=0.0.8)
Requires-Dist: chex (>=0.1.5)
Requires-Dist: optax (>=0.1.3)
Requires-Dist: tensorboard (>=2.9.1)
Requires-Dist: tensorboardX (>=2.5.1)
Requires-Dist: lz4 (>=4.0.1)
Requires-Dist: cloudpickle (>=2.2.0)
Requires-Dist: importlib-metadata (<5.0.0)
Requires-Dist: dm-control (>=1.0.7)
Provides-Extra: dev
Requires-Dist: flake8 (>=3.8.4) ; extra == 'dev'
Requires-Dist: pylint (>=2.6.0) ; extra == 'dev'
Requires-Dist: pur (>=5.3.0) ; extra == 'dev'
Requires-Dist: pytest (>=6.1.2) ; extra == 'dev'
Requires-Dist: pytest-cov (>=2.10.1) ; extra == 'dev'
Requires-Dist: pytest-xdist (>=2.1.0) ; extra == 'dev'
Requires-Dist: twine (>=3.2.0) ; extra == 'dev'
Requires-Dist: jupyter (>=1.0.0) ; extra == 'dev'
Requires-Dist: sphinx-autobuild (>=2020.9.1) ; extra == 'dev'
Provides-Extra: doc
Requires-Dist: jax (>=0.3.25) ; extra == 'doc'
Requires-Dist: jaxlib (>=0.3.25) ; extra == 'doc'
Requires-Dist: Sphinx (>=3.5.4) ; extra == 'doc'
Requires-Dist: sphinx-rtd-theme (>=0.5.0) ; extra == 'doc'
Requires-Dist: nbsphinx (>=0.8.0) ; extra == 'doc'
Requires-Dist: sphinx-tabs (>=1.3.0) ; extra == 'doc'
Requires-Dist: sphinx-copybutton (>=0.3.1) ; extra == 'doc'
Requires-Dist: sphinx-notfound-page (>=0.5) ; extra == 'doc'
Provides-Extra: ray
Requires-Dist: ray (>1.9.0) ; extra == 'ray'
